{
	"version": 6,
	"tables": {
		"activities": [
			{
				"id": "act_fixed_a",
				"category_id": "Work",
				"name": "Meeting A (Fixed)",
				"priority": 1,
				"default_duration": 60,
				"is_replaceable": false,
				"color": "#EF4444",
				"created_at": 1773911273654,
				"_status": "synced"
			},
			{
				"id": "act_fixed_b",
				"category_id": "Work",
				"name": "Meeting B (Fixed)",
				"priority": 1,
				"default_duration": 60,
				"is_replaceable": false,
				"color": "#EF4444",
				"created_at": 1773911273654,
				"_status": "synced"
			},
			{
				"id": "act_high_1",
				"category_id": "Study",
				"name": "High Priority Task 1",
				"priority": 1,
				"default_duration": 60,
				"is_replaceable": true,
				"color": "#2563EB",
				"created_at": 1773911273654,
				"_status": "synced"
			},
			{
				"id": "act_high_2",
				"category_id": "Study",
				"name": "High Priority Task 2",
				"priority": 1,
				"default_duration": 60,
				"is_replaceable": true,
				"color": "#2563EB",
				"created_at": 1773911273654,
				"_status": "synced"
			},
			{
				"id": "act_high_3",
				"category_id": "Study",
				"name": "High Priority Task 3",
				"priority": 1,
				"default_duration": 60,
				"is_replaceable": true,
				"color": "#2563EB",
				"created_at": 1773911273654,
				"_status": "synced"
			}
		],
		"scheduled_events": [
			{
				"id": "ev_bf2uxuvq6b",
				"activity_id": "act_fixed_a",
				"category_id": "Work",
				"title": "Meeting A (Fixed)",
				"start_time": 1774022400000,
				"end_time": 1774026000000,
				"duration": 60,
				"status": "CONFIRMED",
				"replaceability_status": "HARD",
				"priority": 1,
				"is_recurring": false,
				"source": "EXTERNAL_IMPORT",
				"is_locked": true,
				"created_at": 1773911273654,
				"updated_at": 1773911273654,
				"_status": "synced"
			},
			{
				"id": "ev_qkun7k7m19",
				"activity_id": "act_fixed_b",
				"category_id": "Work",
				"title": "Meeting B (Fixed)",
				"start_time": 1774029600000,
				"end_time": 1774033200000,
				"duration": 60,
				"status": "CONFIRMED",
				"replaceability_status": "HARD",
				"priority": 1,
				"is_recurring": false,
				"source": "EXTERNAL_IMPORT",
				"is_locked": true,
				"created_at": 1773911273654,
				"updated_at": 1773911273654,
				"_status": "synced"
			},
			{
				"id": "ev_f09p8d3tkx",
				"activity_id": "act_high_1",
				"category_id": "Study",
				"title": "High Priority Task 1",
				"start_time": 1774026000000,
				"end_time": 1774029600000,
				"duration": 60,
				"status": "CONFIRMED",
				"replaceability_status": "SOFT",
				"priority": 1,
				"is_recurring": false,
				"source": "EXTERNAL_IMPORT",
				"is_locked": false,
				"created_at": 1773911273654,
				"updated_at": 1773911273654,
				"_status": "synced"
			},
			{
				"id": "ev_blqe46wkri",
				"activity_id": "act_high_2",
				"category_id": "Study",
				"title": "High Priority Task 2",
				"start_time": 1774026000000,
				"end_time": 1774029600000,
				"duration": 60,
				"status": "CONFIRMED",
				"replaceability_status": "SOFT",
				"priority": 1,
				"is_recurring": false,
				"source": "EXTERNAL_IMPORT",
				"is_locked": false,
				"created_at": 1773911273654,
				"updated_at": 1773911273654,
				"_status": "synced"
			},
			{
				"id": "ev_yfano9ye2d",
				"activity_id": "act_high_3",
				"category_id": "Study",
				"title": "High Priority Task 3",
				"start_time": 1774026000000,
				"end_time": 1774029600000,
				"duration": 60,
				"status": "CONFIRMED",
				"replaceability_status": "SOFT",
				"priority": 1,
				"is_recurring": false,
				"source": "EXTERNAL_IMPORT",
				"is_locked": false,
				"created_at": 1773911273654,
				"updated_at": 1773911273654,
				"_status": "synced"
			}
		],
		"activity_history": []
	},
	"exportedAt": 1773911273654
}
